dpa/__init__.py
dpa/dpa_fit.py
dpa/model.py
dpa/utils.py
DistributionalPrincipalAutoencoder-0.0.0.dev0.dist-info/LICENSE
DistributionalPrincipalAutoencoder-0.0.0.dev0.dist-info/METADATA
DistributionalPrincipalAutoencoder-0.0.0.dev0.dist-info/WHEEL
DistributionalPrincipalAutoencoder-0.0.0.dev0.dist-info/top_level.txt
DistributionalPrincipalAutoencoder-0.0.0.dev0.dist-info/RECORD
