Metadata-Version: 2.1
Name: DistributionalPrincipalAutoencoder
Version: 0.0.0.dev0
Summary: Distributional Principal Autoencoder
Home-page: https://github.com/xwshen51/DistributionalPrincipalAutoencoder
Author: Xinwei Shen and Nicolai Meinshausen
Author-email: xinwei.shen@stat.math.ethz.ch
License: BSD 3-Clause License
License-File: LICENSE
Requires-Dist: torch
Requires-Dist: numpy
Requires-Dist: matplotlib
Requires-Dist: engression
